CHANGES.txt
CONTRIBUTORS.txt
COPYRIGHT.txt
LICENSE.txt
MANIFEST.in
README.rst
setup.cfg
setup.py
pyramid_amon/__init__.py
pyramid_amon/tests.py
pyramid_amon.egg-info/PKG-INFO
pyramid_amon.egg-info/SOURCES.txt
pyramid_amon.egg-info/dependency_links.txt
pyramid_amon.egg-info/not-zip-safe
pyramid_amon.egg-info/requires.txt
pyramid_amon.egg-info/top_level.txt