Metadata-Version: 1.1
Name: pyramid-amon
Version: 0.1
Summary: Pyramid add-on for Amon application and system monitoring toolkit.
Home-page: http://pylonsproject.org
Author: Blaise Laflamme
Author-email: pylons-discuss@googlegroups.com
License: BSD-derived (http://www.repoze.org/LICENSE.txt)
Keywords: wsgi pylons web pyramid
Platform: UNKNOWN
Classifier: Intended Audience :: Developers
Classifier: Programming Language :: Python
Classifier: Framework :: Pyramid
Classifier: License :: Repoze Public License
Classifier: Programming Language :: Python :: 2.6
Classifier: Programming Language :: Python :: 2.7
Classifier: Programming Language :: Python :: 3.2
Classifier: Programming Language :: Python :: 3.3
